odoo8_addon_purchase_delivery_address-8.0.1.1.0-py2.7-nspkg.pth
odoo8_addon_purchase_delivery_address-8.0.1.1.0.dist-info/top_level.txt
odoo8_addon_purchase_delivery_address-8.0.1.1.0.dist-info/WHEEL
odoo8_addon_purchase_delivery_address-8.0.1.1.0.dist-info/RECORD
odoo8_addon_purchase_delivery_address-8.0.1.1.0.dist-info/metadata.json
odoo8_addon_purchase_delivery_address-8.0.1.1.0.dist-info/DESCRIPTION.rst
odoo8_addon_purchase_delivery_address-8.0.1.1.0.dist-info/METADATA
odoo8_addon_purchase_delivery_address-8.0.1.1.0.dist-info/namespace_packages.txt
odoo_addons/purchase_delivery_address/__openerp__.py
odoo_addons/purchase_delivery_address/__init__.py
odoo_addons/purchase_delivery_address/README.rst
odoo_addons/purchase_delivery_address/i18n/purchase_delivery_address.pot
odoo_addons/purchase_delivery_address/i18n/fr.po
odoo_addons/purchase_delivery_address/static/description/icon.png
