Metadata-Version: 2.0
Name: odoo8-addon-purchase-delivery-address
Version: 8.0.1.1.0
Summary: Deprecated: install purchase_transport_multi_address and stock_transport_multi_address instead
Home-page: UNKNOWN
Author: UNKNOWN
Author-email: UNKNOWN
License: AGPL-3
Platform: UNKNOWN
Requires-Dist: odoo (<9.0a,>=8.0a)
Requires-Dist: odoo8-addon-purchase-transport-multi-address
Requires-Dist: odoo8-addon-stock-transport-multi-address
Classifier: Programming Language :: Python :: 2.7
Classifier: Framework :: Odoo
Classifier: License :: OSI Approved :: GNU Affero General Public License v3
